beets_logimport-0.1.0.dist-info/licenses/LICENSE
beetsplug/__init__.py
beetsplug/logimport.py
beets_logimport-0.1.0.dist-info/METADATA
beets_logimport-0.1.0.dist-info/WHEEL
beets_logimport-0.1.0.dist-info/top_level.txt
beets_logimport-0.1.0.dist-info/RECORD
